ansys/tools/common/__init__.py
ansys/tools/common/cyberchannel.py
ansys/tools/common/example_download.py
ansys/tools/common/exceptions.py
ansys/tools/common/logger.py
ansys/tools/common/logger_formatter.py
ansys/tools/common/py.typed
ansys/tools/common/report.py
ansys/tools/common/versioning.py
ansys/tools/common/abstractions/__init__.py
ansys/tools/common/abstractions/connection.py
ansys/tools/common/abstractions/launcher.py
ansys/tools/common/launcher/__init__.py
ansys/tools/common/launcher/_cli.py
ansys/tools/common/launcher/_plugins.py
ansys/tools/common/launcher/config.py
ansys/tools/common/launcher/grpc_transport.py
ansys/tools/common/launcher/interface.py
ansys/tools/common/launcher/launch.py
ansys/tools/common/launcher/product_instance.py
ansys/tools/common/launcher/py.typed
ansys/tools/common/launcher/helpers/__init__.py
ansys/tools/common/launcher/helpers/grpc.py
ansys/tools/common/launcher/helpers/ports.py
ansys/tools/common/path/__init__.py
ansys/tools/common/path/path.py
ansys/tools/common/path/save.py
ansys/tools/common/path/applications/__init__.py
ansys/tools/common/path/applications/dyna.py
ansys/tools/common/path/applications/mapdl.py
ansys/tools/common/path/applications/mechanical.py
ansys_tools_common-0.4.2.dist-info/METADATA
ansys_tools_common-0.4.2.dist-info/WHEEL
ansys_tools_common-0.4.2.dist-info/entry_points.txt
ansys_tools_common-0.4.2.dist-info/licenses/LICENSE
ansys_tools_common-0.4.2.dist-info/RECORD
