Metadata-Version: 2.4
Name: ansys-tools-common
Version: 0.4.2
Summary: A set of tools for PyAnsys libraries
Project-URL: Discussions, https://github.com/ansys/ansys-tools-common/discussions
Project-URL: Documentation, https://ansys.tools.docs.pyansys.com/
Project-URL: Issues, https://github.com/ansys/ansys-tools-common/issues
Project-URL: Releases, https://github.com/ansys/ansys-tools-common/releases/
Project-URL: Source, https://github.com/ansys/ansys-tools-common
Author-email: "ANSYS, Inc." <pyansys.core@ansys.com>
Maintainer-email: "ANSYS, Inc." <pyansys.core@ansys.com>
License-Expression: MIT
License-File: LICENSE
Classifier: Development Status :: 4 - Beta
Classifier: Intended Audience :: Science/Research
Classifier: Operating System :: OS Independent
Classifier: Programming Language :: Python :: 3 :: Only
Classifier: Programming Language :: Python :: 3.10
Classifier: Programming Language :: Python :: 3.11
Classifier: Programming Language :: Python :: 3.12
Classifier: Programming Language :: Python :: 3.13
Classifier: Programming Language :: Python :: 3.14
Classifier: Topic :: Scientific/Engineering :: Information Analysis
Requires-Python: <4,>=3.10
Requires-Dist: click>=8.1.3
Requires-Dist: platformdirs>=3.6
Requires-Dist: requests>=2.32.4
Requires-Dist: scooby>=0.5.12
Requires-Dist: typing-extensions>=4.5
Provides-Extra: all
Requires-Dist: ansys-tools-filetransfer>=0.1.1; extra == 'all'
Requires-Dist: ansys-tools-visualization-interface>=0.9.2; extra == 'all'
Provides-Extra: filetransfer
Requires-Dist: ansys-tools-filetransfer>=0.1.1; extra == 'filetransfer'
Provides-Extra: graphics
Requires-Dist: ansys-tools-visualization-interface>=0.9.2; extra == 'graphics'
